easykvchat/__init__.py
easykvchat/main.py
easykvchat/memberspannel.kv
easykvchat/memberspannel.py
easykvchat/roomlogs.kv
easykvchat/roomlogs.py
easykvchat/client/app.py
easykvchat/client/client.kv
easykvchat/client/network.py
easykvchat/server/app.py
easykvchat/server/network.py
easykvchat/server/server.kv
easykvchat-1.0.0.dist-info/LICENSE
easykvchat-1.0.0.dist-info/METADATA
easykvchat-1.0.0.dist-info/WHEEL
easykvchat-1.0.0.dist-info/top_level.txt
easykvchat-1.0.0.dist-info/RECORD
