Metadata-Version: 2.1
Name: easykvchat
Version: 1.0.0
Summary: Ensemble client/serveur d'un système de messagerie.
Home-page: UNKNOWN
Author: ThisALV
Author-email: lel.charriere@orange.fr
License: UNKNOWN
Platform: UNKNOWN
Classifier: Programming Language :: Python :: 3
Classifier: License :: OSI Approved :: MIT License
Classifier: Operating System :: OS Independent
Classifier: Natural Language :: French
Classifier: Topic :: Communications :: Chat
Requires-Python: >=3.8
Requires-Dist: kivy
Requires-Dist: Twisted
